vhdl/counter/counter.vhdl
entity Counter is
	port(
		clock: in  bit;
		reset: in  bit;
		count: out natural
	);
end entity;

architecture sync of Counter is
	signal cnt: natural;
begin
	process(clock) begin if rising_edge(clock) then
		if reset then
			count <= 0;
		else
			count <= count + 1;
		end if;
	end if; end process;
end architecture;

vhdl/counter/sim.vhdl
use std.env;

entity CounterSim is
end entity;

architecture sim of CounterSim is
	signal clk:  bit;
	signal rst:  bit;
	signal data: natural;
	signal eos:  boolean;
begin
	-- Instantiation of the DUT
	dut: entity work.Counter(sync)
	port map(
		clock => clk,
		reset => rst,
		count => data
	);

	-- A clock generating process with a 2ns clock period.
	-- Infinite loop, the clock will never stop toggling.
	process
	begin
		clk <= '0';
		wait for 1 ns;
		clk <= '1';
		wait for 1 ns;
	end process;

	-- The process that handles the reset: active
	-- until the 5th rising edge of the clock.
	process
	begin
		rst  <= '1';
		for i in 1 to 5 loop
 			wait until rising_edge(clk);
		end loop;
		rst  <= '0';
		for i in 1 to 20 loop
			wait until rising_edge(clk);
		end loop;
		env.finish;
	end process;
end architecture;

vhdl/counter/sim.vcd
$date
  Tue Dec 29 19:50:03 2020
$end
$version
  GHDL v0
$end
$timescale
  1 fs
$end
$scope module standard $end
$upscope $end
$scope module env $end
$upscope $end
$scope module countersim $end
$var reg 1 ! clk $end
$var reg 1 " rst $end
$var integer 32 # data $end
$var reg 1 $ eos $end
$scope module dut $end
$var reg 1 % clock $end
$var reg 1 & reset $end
$var integer 32 ' count $end
$var integer 32 ( cnt $end
$upscope $end
$upscope $end
$enddefinitions $end
#0
0!
1"
b0 #
0$
0%
1&
b0 '
b0 (
#1000000
1!
1%
#2000000
0!
0%
#3000000
1!
1%
#4000000
0!
0%
#5000000
1!
1%
#6000000
0!
0%
#7000000
1!
1%
#8000000
0!
0%
#9000000
1!
0"
1%
0&
#10000000
0!
0%
#11000000
1!
b1 #
1%
b1 '
#12000000
0!
0%
#13000000
1!
b10 #
1%
b10 '
#14000000
0!
0%
#15000000
1!
b11 #
1%
b11 '
#16000000
0!
0%
#17000000
1!
b100 #
1%
b100 '
#18000000
0!
0%
#19000000
1!
b101 #
1%
b101 '
#20000000
0!
0%
#21000000
1!
b110 #
1%
b110 '
#22000000
0!
0%
#23000000
1!
b111 #
1%
b111 '
#24000000
0!
0%
#25000000
1!
b1000 #
1%
b1000 '
#26000000
0!
0%
#27000000
1!
b1001 #
1%
b1001 '
#28000000
0!
0%
#29000000
1!
b1010 #
1%
b1010 '
#30000000
0!
0%
#31000000
1!
b1011 #
1%
b1011 '
#32000000
0!
0%
#33000000
1!
b1100 #
1%
b1100 '
#34000000
0!
0%
#35000000
1!
b1101 #
1%
b1101 '
#36000000
0!
0%
#37000000
1!
b1110 #
1%
b1110 '
#38000000
0!
0%
#39000000
1!
b1111 #
1%
b1111 '
#40000000
0!
0%
#41000000
1!
b10000 #
1%
b10000 '
#42000000
0!
0%
#43000000
1!
b10001 #
1%
b10001 '
#44000000
0!
0%
#45000000
1!
b10010 #
1%
b10010 '
#46000000
0!
0%
#47000000
1!
b10011 #
1%
b10011 '
